Workbook

Sheet Assumptions
A1: Japan NatCat Reinsurance Pricing Workbook
A2: All blue values are adjustable inputs. Black values are calculated.
A4: EXCESS OF LOSS (XoL) LAYER DEFINITIONS
A5: Layer | B5: Attachment (¥B) | C5: Limit (¥B) | D5: Description
A6: Layer 1 (Working) | B6: 10 | C6: 20 | D6: Frequency layer — smaller, more frequent cat losses
A7: Layer 2 (Mid) | B7: 30 | C7: 30 | D7: Mid-severity events (e.g., major typhoon)
A8: Layer 3 (Cat) | B8: 60 | C8: 40 | D8: Severe events (e.g., M7+ earthquake near metro)
A9: Layer 4 (Remote) | B9: 100 | C9: 50 | D9: Peak peril / tail risk protection
A12: QUOTA SHARE PARAMETERS
A13: Parameter | B13: Value | C13: Unit | D13: Description
A14: Cession Percentage | B14: 0.3 | C14: % | D14: Proportion of every loss ceded to reinsurer
A15: Ceding Commission | B15: 0.25 | C15: % | D15: Commission paid back to cedent by reinsurer
A18: PRICING PARAMETERS
A19: Parameter | B19: Value | C19: Unit | D19: Description
A20: Loading Factor (Profit + Expenses) | B20: 0.35 | C20: x | D20: Applied on top of expected loss
A21: Brokerage Fee | B21: 0.1 | C21: % | D21: Broker commission (e.g., Gallagher Re)
A22: Monte Carlo Scenarios (conceptual) | B22: 10000 | C22: # | D22: Number of simulated years

Sheet Exposure Portfolio
A1: Hypothetical Japanese Property Insurance Portfolio
A2: Source: Prefecture GDP weights (Cabinet Office), Construction type assumptions based on published GIROJ data
A4: Region / Prefecture | B4: TSI (¥ Billion) | C4: Occupancy | D4: Construction | E4: EQ Deductible % | F4: Wind Deductible % | G4: Portfolio Share
A5: Tokyo (東京) | B5: 450 | C5: Commercial/Residential | D5: SRC / RC | E5: 0.05 | F5: 0.03 | G5: =B5/B21 -> 0.225
A6: Kanagawa (神奈川) | B6: 180 | C6: Commercial/Residential | D6: RC / Wood | E6: 0.05 | F6: 0.03 | G6: =B6/B21 -> 0.09
A7: Osaka (大阪) | B7: 200 | C7: Commercial/Residential | D7: SRC / RC | E7: 0.05 | F7: 0.03 | G7: =B7/B21 -> 0.1
A8: Aichi (愛知) | B8: 160 | C8: Industrial/Commercial | D8: Steel / RC | E8: 0.05 | F8: 0.03 | G8: =B8/B21 -> 0.08
A9: Fukuoka (福岡) | B9: 90 | C9: Commercial/Residential | D9: RC / Wood | E9: 0.05 | F9: 0.04 | G9: =B9/B21 -> 0.045
A10: Hokkaido (北海道) | B10: 70 | C10: Residential/Agricultural | D10: Wood / RC | E10: 0.03 | F10: 0.04 | G10: =B10/B21 -> 0.035
A11: Miyagi (宮城) | B11: 55 | C11: Commercial/Residential | D11: RC / Wood | E11: 0.07 | F11: 0.04 | G11: =B11/B21 -> 0.0275
A12: Hyogo (兵庫) | B12: 85 | C12: Commercial/Residential | D12: SRC / RC | E12: 0.05 | F12: 0.03 | G12: =B12/B21 -> 0.0425
A13: Chiba (千葉) | B13: 95 | C13: Residential/Commercial | D13: Wood / RC | E13: 0.05 | F13: 0.04 | G13: =B13/B21 -> 0.0475
A14: Saitama (埼玉) | B14: 100 | C14: Residential/Commercial | D14: Wood / RC | E14: 0.05 | F14: 0.03 | G14: =B14/B21 -> 0.05
A15: Shizuoka (静岡) | B15: 75 | C15: Industrial/Residential | D15: Steel / RC | E15: 0.07 | F15: 0.04 | G15: =B15/B21 -> 0.0375
A16: Hiroshima (広島) | B16: 55 | C16: Commercial/Residential | D16: RC / Wood | E16: 0.05 | F16: 0.04 | G16: =B16/B21 -> 0.0275
A17: Niigata (新潟) | B17: 35 | C17: Residential/Agricultural | D17: Wood | E17: 0.05 | F17: 0.04 | G17: =B17/B21 -> 0.0175
A18: Kumamoto (熊本) | B18: 25 | C18: Residential/Agricultural | D18: Wood | E18: 0.07 | F18: 0.05 | G18: =B18/B21 -> 0.0125
A19: Okinawa (沖縄) | B19: 20 | C19: Residential | D19: RC | E19: 0.03 | F19: 0.06 | G19: =B19/B21 -> 0.01
A20: Other Prefectures | B20: 305 | C20: Mixed | D20: Mixed | E20: 0.05 | F20: 0.04 | G20: =B20/B21 -> 0.1525
A21: TOTAL PORTFOLIO | B21: =SUM(B5:B20) -> 2000 | G21: =SUM(G5:G20) -> 1

Sheet Loss Scenarios
A1: Historical & Hypothetical Catastrophe Loss Scenarios
A2: Loss estimates are illustrative, calibrated to publicly reported insured loss ranges. Sources: Swiss Re Sigma, GIROJ, Industry reports.
A4: Year | B4: Event | C4: Peril | D4: JMA Intensity / Category | E4: Gross Loss (¥B) | F4: After Deductible (¥B) | G4: Return Period (est.)
A5: 2011 | B5: Tohoku Earthquake & Tsunami (東日本大震災) | C5: EQ | D5: M9.0 / Shindo 7 | E5: 280 | F5: =E5*(1-0.05) -> 266 | G5: ~500 yr
A6: 2018 | B6: Typhoon Jebi (台風21号) | C6: WS | D6: Cat 4 equivalent | E6: 95 | F6: =E6*(1-0.05) -> 90.25 | G6: ~50 yr
A7: 2019 | B7: Typhoon Hagibis (台風19号) | C7: WS | D7: Cat 4 equivalent | E7: 75 | F7: =E7*(1-0.05) -> 71.25 | G7: ~40 yr
A8: 2016 | B8: Kumamoto Earthquake (熊本地震) | C8: EQ | D8: M7.3 / Shindo 7 | E8: 35 | F8: =E8*(1-0.05) -> 33.25 | G8: ~80 yr
A9: 2018 | B9: Osaka Earthquake (大阪北部地震) | C9: EQ | D9: M6.1 / Shindo 6+ | E9: 12 | F9: =E9*(1-0.05) -> 11.4 | G9: ~30 yr
A10: 2004 | B10: Typhoon Tokage (台風23号) | C10: WS | D10: Cat 3 equivalent | E10: 18 | F10: =E10*(1-0.05) -> 17.1 | G10: ~20 yr
A11: 1995 | B11: Kobe Earthquake (阪神・淡路大震災) | C11: EQ | D11: M7.3 / Shindo 7 | E11: 200 | F11: =E11*(1-0.05) -> 190 | G11: ~200 yr
A12: Hypo-A | B12: Nankai Trough Scenario (南海トラフ) | C12: EQ | D12: M8.5+ / Shindo 7 | E12: 500 | F12: =E12*(1-0.05) -> 475 | G12: ~150 yr
A13: Hypo-B | B13: Tokyo Inland EQ (首都直下地震) | C13: EQ | D13: M7.3 / Shindo 7 | E13: 350 | F13: =E13*(1-0.05) -> 332.5 | G13: ~200 yr
A14: Hypo-C | B14: Super Typhoon Tokyo Direct Hit | C14: WS | D14: Cat 5 equivalent | E14: 150 | F14: =E14*(1-0.05) -> 142.5 | G14: ~100 yr
A15: Hypo-D | B15: Moderate Typhoon Season (multiple) | C15: WS | D15: Cat 2-3 aggregate | E15: 45 | F15: =E15*(1-0.05) -> 42.75 | G15: ~10 yr
A16: Hypo-E | B16: Minor EQ Swarm (freq. losses) | C16: EQ | D16: M5-6 multiple | E16: 8 | F16: =E16*(1-0.05) -> 7.6 | G16: ~5 yr

Sheet Reinsurance Structures
A1: Reinsurance Structure Comparison — Per-Event Loss Allocation
A2: All formulas reference Assumptions sheet for layer definitions and Loss Scenarios sheet for gross losses.
A4: A. EXCESS OF LOSS — PER-EVENT ALLOCATION
A5: Event | B5: Net Loss (¥B) | C5: L1: Cedent Retains | D5: L1: Reinsurer Pays | E5: L2: Cedent Retains | F5: L2: Reinsurer Pays | G5: L3: Cedent Retains | H5: L3: Reinsurer Pays
A6: ='Loss Scenarios'!B5 -> Tohoku Earthquake & Tsunami (東日本大震災) | B6: ='Loss Scenarios'!F5 -> 266 | C6: =MIN(B6, Assumptions!B6) -> 10 | D6: =MIN(MAX(B6-Assumptions!B6, 0), Assumptions!C6) -> 20 | E6: =B6-C6-D6-F6-H6 -> 166 | F6: =MIN(MAX(B6-Assumptions!B7, 0), Assumptions!C7) -> 30 | G6: =B6-D6-F6-H6 -> 176 | H6: =MIN(MAX(B6-Assumptions!B8, 0), Assumptions!C8) -> 40
A7: ='Loss Scenarios'!B6 -> Typhoon Jebi (台風21号) | B7: ='Loss Scenarios'!F6 -> 90.25 | C7: =MIN(B7, Assumptions!B6) -> 10 | D7: =MIN(MAX(B7-Assumptions!B6, 0), Assumptions!C6) -> 20 | E7: =B7-C7-D7-F7-H7 -> 0 | F7: =MIN(MAX(B7-Assumptions!B7, 0), Assumptions!C7) -> 30 | G7: =B7-D7-F7-H7 -> 10 | H7: =MIN(MAX(B7-Assumptions!B8, 0), Assumptions!C8) -> 30.25
A8: ='Loss Scenarios'!B7 -> Typhoon Hagibis (台風19号) | B8: ='Loss Scenarios'!F7 -> 71.25 | C8: =MIN(B8, Assumptions!B6) -> 10 | D8: =MIN(MAX(B8-Assumptions!B6, 0), Assumptions!C6) -> 20 | E8: =B8-C8-D8-F8-H8 -> 0 | F8: =MIN(MAX(B8-Assumptions!B7, 0), Assumptions!C7) -> 30 | G8: =B8-D8-F8-H8 -> 10 | H8: =MIN(MAX(B8-Assumptions!B8, 0), Assumptions!C8) -> 11.25
A9: ='Loss Scenarios'!B8 -> Kumamoto Earthquake (熊本地震) | B9: ='Loss Scenarios'!F8 -> 33.25 | C9: =MIN(B9, Assumptions!B6) -> 10 | D9: =MIN(MAX(B9-Assumptions!B6, 0), Assumptions!C6) -> 20 | E9: =B9-C9-D9-F9-H9 -> 0 | F9: =MIN(MAX(B9-Assumptions!B7, 0), Assumptions!C7) -> 3.25 | G9: =B9-D9-F9-H9 -> 10 | H9: =MIN(MAX(B9-Assumptions!B8, 0), Assumptions!C8) -> 0
A10: ='Loss Scenarios'!B9 -> Osaka Earthquake (大阪北部地震) | B10: ='Loss Scenarios'!F9 -> 11.4 | C10: =MIN(B10, Assumptions!B6) -> 10 | D10: =MIN(MAX(B10-Assumptions!B6, 0), Assumptions!C6) -> 1.4 | E10: =B10-C10-D10-F10-H10 -> 0 | F10: =MIN(MAX(B10-Assumptions!B7, 0), Assumptions!C7) -> 0 | G10: =B10-D10-F10-H10 -> 10 | H10: =MIN(MAX(B10-Assumptions!B8, 0), Assumptions!C8) -> 0
A11: ='Loss Scenarios'!B10 -> Typhoon Tokage (台風23号) | B11: ='Loss Scenarios'!F10 -> 17.1 | C11: =MIN(B11, Assumptions!B6) -> 10 | D11: =MIN(MAX(B11-Assumptions!B6, 0), Assumptions!C6) -> 7.1 | E11: =B11-C11-D11-F11-H11 -> 0 | F11: =MIN(MAX(B11-Assumptions!B7, 0), Assumptions!C7) -> 0 | G11: =B11-D11-F11-H11 -> 10 | H11: =MIN(MAX(B11-Assumptions!B8, 0), Assumptions!C8) -> 0
A12: ='Loss Scenarios'!B11 -> Kobe Earthquake (阪神・淡路大震災) | B12: ='Loss Scenarios'!F11 -> 190 | C12: =MIN(B12, Assumptions!B6) -> 10 | D12: =MIN(MAX(B12-Assumptions!B6, 0), Assumptions!C6) -> 20 | E12: =B12-C12-D12-F12-H12 -> 90 | F12: =MIN(MAX(B12-Assumptions!B7, 0), Assumptions!C7) -> 30 | G12: =B12-D12-F12-H12 -> 100 | H12: =MIN(MAX(B12-Assumptions!B8, 0), Assumptions!C8) -> 40
A13: ='Loss Scenarios'!B12 -> Nankai Trough Scenario (南海トラフ) | B13: ='Loss Scenarios'!F12 -> 475 | C13: =MIN(B13, Assumptions!B6) -> 10 | D13: =MIN(MAX(B13-Assumptions!B6, 0), Assumptions!C6) -> 20 | E13: =B13-C13-D13-F13-H13 -> 375 | F13: =MIN(MAX(B13-Assumptions!B7, 0), Assumptions!C7) -> 30 | G13: =B13-D13-F13-H13 -> 385 | H13: =MIN(MAX(B13-Assumptions!B8, 0), Assumptions!C8) -> 40
A14: ='Loss Scenarios'!B13 -> Tokyo Inland EQ (首都直下地震) | B14: ='Loss Scenarios'!F13 -> 332.5 | C14: =MIN(B14, Assumptions!B6) -> 10 | D14: =MIN(MAX(B14-Assumptions!B6, 0), Assumptions!C6) -> 20 | E14: =B14-C14-D14-F14-H14 -> 232.5 | F14: =MIN(MAX(B14-Assumptions!B7, 0), Assumptions!C7) -> 30 | G14: =B14-D14-F14-H14 -> 242.5 | H14: =MIN(MAX(B14-Assumptions!B8, 0), Assumptions!C8) -> 40
A15: ='Loss Scenarios'!B14 -> Super Typhoon Tokyo Direct Hit | B15: ='Loss Scenarios'!F14 -> 142.5 | C15: =MIN(B15, Assumptions!B6) -> 10 | D15: =MIN(MAX(B15-Assumptions!B6, 0), Assumptions!C6) -> 20 | E15: =B15-C15-D15-F15-H15 -> 42.5 | F15: =MIN(MAX(B15-Assumptions!B7, 0), Assumptions!C7) -> 30 | G15: =B15-D15-F15-H15 -> 52.5 | H15: =MIN(MAX(B15-Assumptions!B8, 0), Assumptions!C8) -> 40
A16: ='Loss Scenarios'!B15 -> Moderate Typhoon Season (multiple) | B16: ='Loss Scenarios'!F15 -> 42.75 | C16: =MIN(B16, Assumptions!B6) -> 10 | D16: =MIN(MAX(B16-Assumptions!B6, 0), Assumptions!C6) -> 20 | E16: =B16-C16-D16-F16-H16 -> 0 | F16: =MIN(MAX(B16-Assumptions!B7, 0), Assumptions!C7) -> 12.75 | G16: =B16-D16-F16-H16 -> 10 | H16: =MIN(MAX(B16-Assumptions!B8, 0), Assumptions!C8) -> 0
A17: ='Loss Scenarios'!B16 -> Minor EQ Swarm (freq. losses) | B17: ='Loss Scenarios'!F16 -> 7.6 | C17: =MIN(B17, Assumptions!B6) -> 7.6 | D17: =MIN(MAX(B17-Assumptions!B6, 0), Assumptions!C6) -> 0 | E17: =B17-C17-D17-F17-H17 -> 0 | F17: =MIN(MAX(B17-Assumptions!B7, 0), Assumptions!C7) -> 0 | G17: =B17-D17-F17-H17 -> 7.6 | H17: =MIN(MAX(B17-Assumptions!B8, 0), Assumptions!C8) -> 0
A19: AVERAGE (proxy for AAL) | B19: =AVERAGE(B6:B17) -> 139.96667 | C19: =AVERAGE(C6:C17) -> 9.8 | D19: =AVERAGE(D6:D17) -> 15.708333 | E19: =AVERAGE(E6:E17) -> 75.5 | F19: =AVERAGE(F6:F17) -> 18.833333 | G19: =AVERAGE(G6:G17) -> 85.3 | H19: =AVERAGE(H6:H17) -> 20.125
A20: MAX (worst case) | B20: =MAX(B6:B17) -> 475 | C20: =MAX(C6:C17) -> 10 | D20: =MAX(D6:D17) -> 20 | E20: =MAX(E6:E17) -> 375 | F20: =MAX(F6:F17) -> 30 | G20: =MAX(G6:G17) -> 385 | H20: =MAX(H6:H17) -> 40
A23: B. QUOTA SHARE — PER-EVENT ALLOCATION
A24: Event | B24: Net Loss (¥B) | C24: Cedent Retains (¥B) | D24: Reinsurer Pays (¥B)
A25: ='Loss Scenarios'!B5 -> Tohoku Earthquake & Tsunami (東日本大震災) | B25: ='Loss Scenarios'!F5 -> 266 | C25: =B25*(1-Assumptions!B14) -> 186.2 | D25: =B25*Assumptions!B14 -> 79.8
A26: ='Loss Scenarios'!B6 -> Typhoon Jebi (台風21号) | B26: ='Loss Scenarios'!F6 -> 90.25 | C26: =B26*(1-Assumptions!B14) -> 63.175 | D26: =B26*Assumptions!B14 -> 27.075
A27: ='Loss Scenarios'!B7 -> Typhoon Hagibis (台風19号) | B27: ='Loss Scenarios'!F7 -> 71.25 | C27: =B27*(1-Assumptions!B14) -> 49.875 | D27: =B27*Assumptions!B14 -> 21.375
A28: ='Loss Scenarios'!B8 -> Kumamoto Earthquake (熊本地震) | B28: ='Loss Scenarios'!F8 -> 33.25 | C28: =B28*(1-Assumptions!B14) -> 23.275 | D28: =B28*Assumptions!B14 -> 9.975
A29: ='Loss Scenarios'!B9 -> Osaka Earthquake (大阪北部地震) | B29: ='Loss Scenarios'!F9 -> 11.4 | C29: =B29*(1-Assumptions!B14) -> 7.98 | D29: =B29*Assumptions!B14 -> 3.42
A30: ='Loss Scenarios'!B10 -> Typhoon Tokage (台風23号) | B30: ='Loss Scenarios'!F10 -> 17.1 | C30: =B30*(1-Assumptions!B14) -> 11.97 | D30: =B30*Assumptions!B14 -> 5.13
A31: ='Loss Scenarios'!B11 -> Kobe Earthquake (阪神・淡路大震災) | B31: ='Loss Scenarios'!F11 -> 190 | C31: =B31*(1-Assumptions!B14) -> 133 | D31: =B31*Assumptions!B14 -> 57
A32: ='Loss Scenarios'!B12 -> Nankai Trough Scenario (南海トラフ) | B32: ='Loss Scenarios'!F12 -> 475 | C32: =B32*(1-Assumptions!B14) -> 332.5 | D32: =B32*Assumptions!B14 -> 142.5
A33: ='Loss Scenarios'!B13 -> Tokyo Inland EQ (首都直下地震) | B33: ='Loss Scenarios'!F13 -> 332.5 | C33: =B33*(1-Assumptions!B14) -> 232.75 | D33: =B33*Assumptions!B14 -> 99.75
A34: ='Loss Scenarios'!B14 -> Super Typhoon Tokyo Direct Hit | B34: ='Loss Scenarios'!F14 -> 142.5 | C34: =B34*(1-Assumptions!B14) -> 99.75 | D34: =B34*Assumptions!B14 -> 42.75
A35: ='Loss Scenarios'!B15 -> Moderate Typhoon Season (multiple) | B35: ='Loss Scenarios'!F15 -> 42.75 | C35: =B35*(1-Assumptions!B14) -> 29.925 | D35: =B35*Assumptions!B14 -> 12.825
A36: ='Loss Scenarios'!B16 -> Minor EQ Swarm (freq. losses) | B36: ='Loss Scenarios'!F16 -> 7.6 | C36: =B36*(1-Assumptions!B14) -> 5.32 | D36: =B36*Assumptions!B14 -> 2.28
A37: AVERAGE | B37: =AVERAGE(B25:B36) -> 139.96667 | C37: =AVERAGE(C25:C36) -> 97.976667 | D37: =AVERAGE(D25:D36) -> 41.99

Sheet Pricing & Comparison
A1: Reinsurance Pricing Summary & Structure Comparison
A3: A. XoL LAYER PRICING
A4: Metric | B4: Layer 1 ¥10B xs ¥10B | C4: Layer 2 ¥30B xs ¥30B | D4: Layer 3 ¥40B xs ¥60B | E4: Total XoL Program
A5: Expected Ceded Loss (¥B) | B5: ='Reinsurance Structures'!D19 -> 15.708333 | C5: ='Reinsurance Structures'!F19 -> 18.833333 | D5: ='Reinsurance Structures'!H19 -> 20.125 | E5: =B5+C5+D5 -> 54.666667
A6: Layer Limit (¥B) | B6: =Assumptions!C6 -> 20 | C6: =Assumptions!C7 -> 30 | D6: =Assumptions!C8 -> 40 | E6: =B6+C6+D6 -> 90
A7: Rate on Line (ROL) | B7: =B5/B6 -> 0.78541667 | C7: =C5/C6 -> 0.62777778 | D7: =D5/D6 -> 0.503125 | E7: =E5/E6 -> 0.60740741
A8: Technical Premium (¥B) | B8: =B5*(1+Assumptions!B20) -> 21.20625 | C8: =C5*(1+Assumptions!B20) -> 25.425 | D8: =D5*(1+Assumptions!B20) -> 27.16875 | E8: =B8+C8+D8 -> 73.8
A9: Less: Brokerage (¥B) | B9: =B8*Assumptions!B21 -> 2.120625 | C9: =C8*Assumptions!B21 -> 2.5425 | D9: =D8*Assumptions!B21 -> 2.716875 | E9: =B9+C9+D9 -> 7.38
A10: Net Premium to Reinsurer (¥B) | B10: =B8-B9 -> 19.085625 | C10: =C8-C9 -> 22.8825 | D10: =D8-D9 -> 24.451875 | E10: =B10+C10+D10 -> 66.42
A13: B. QUOTA SHARE PRICING
A14: Metric | B14: Quota Share 30%
A15: Expected Ceded Loss (¥B) | B15: ='Reinsurance Structures'!D37 -> 41.99
A16: Cession Percentage | B16: =Assumptions!B14 -> 0.3
A17: Technical Premium (¥B) | B17: =B15*(1+Assumptions!B20) -> 56.6865
A18: Less: Ceding Commission (¥B) | B18: =B17*Assumptions!B15 -> 14.171625
A19: Less: Brokerage (¥B) | B19: =(B17-B18)*Assumptions!B21 -> 4.2514875
A20: Net Premium to Reinsurer (¥B) | B20: =B17-B18-B19 -> 38.263388
A23: C. HEAD-TO-HEAD: XoL PROGRAM vs QUOTA SHARE
A24: Metric | B24: XoL Program | C24: Quota Share 30% | D24: Broker Recommendation
A25: Total Premium Cost (¥B) | B25: =E8 -> 73.8 | C25: =B17 -> 56.6865 | D25: =IF(B25<C25, "XoL cheaper", "QS cheaper") -> QS cheaper
A26: Avg Ceded Loss (¥B) | B26: =E5 -> 54.666667 | C26: =B15 -> 41.99 | D26: =IF(B26>C26, "XoL cedes more", "QS cedes more") -> XoL cedes more
A27: Max Single-Event Cedent Retention | B27: ='Reinsurance Structures'!G20+'Reinsurance Structures'!C20+'Reinsurance Structures'!E20 -> 770 | C27: ='Reinsurance Structures'!C38 -> 0 | D27: =IF(B27<C27, "XoL protects tail better", "QS protects tail better") -> QS protects tail better
A28: Cost per ¥1B Ceded Loss | B28: =B25/B26 -> 1.35 | C28: =C25/C26 -> 1.35 | D28: =IF(B28<C28, "XoL more efficient", "QS more efficient") -> QS more efficient

Sheet Sensitivity Analysis
A1: Sensitivity Analysis: How Structure Parameters Affect Cedent Cost & Protection
A3: A. QUOTA SHARE — VARYING CESSION PERCENTAGE
A4: Cession % | B4: Avg Ceded Loss (¥B) | C4: Premium (¥B) | D4: Cedent Max Retention (¥B) | E4: Cost Efficiency
A5: 0.1 | B5: =AVERAGE('Loss Scenarios'!F5:F16)*A5 -> 13.996667 | C5: =B5*(1+Assumptions!B20)*(1-Assumptions!B15) -> 14.171625 | D5: =MAX('Loss Scenarios'!F5:F16)*(1-A5) -> 427.5 | E5: =IF(B5=0,0,C5/B5) -> 1.0125
A6: 0.2 | B6: =AVERAGE('Loss Scenarios'!F5:F16)*A6 -> 27.993333 | C6: =B6*(1+Assumptions!B20)*(1-Assumptions!B15) -> 28.34325 | D6: =MAX('Loss Scenarios'!F5:F16)*(1-A6) -> 380 | E6: =IF(B6=0,0,C6/B6) -> 1.0125
A7: 0.25 | B7: =AVERAGE('Loss Scenarios'!F5:F16)*A7 -> 34.991667 | C7: =B7*(1+Assumptions!B20)*(1-Assumptions!B15) -> 35.429063 | D7: =MAX('Loss Scenarios'!F5:F16)*(1-A7) -> 356.25 | E7: =IF(B7=0,0,C7/B7) -> 1.0125
A8: 0.3 | B8: =AVERAGE('Loss Scenarios'!F5:F16)*A8 -> 41.99 | C8: =B8*(1+Assumptions!B20)*(1-Assumptions!B15) -> 42.514875 | D8: =MAX('Loss Scenarios'!F5:F16)*(1-A8) -> 332.5 | E8: =IF(B8=0,0,C8/B8) -> 1.0125
A9: 0.35 | B9: =AVERAGE('Loss Scenarios'!F5:F16)*A9 -> 48.988333 | C9: =B9*(1+Assumptions!B20)*(1-Assumptions!B15) -> 49.600687 | D9: =MAX('Loss Scenarios'!F5:F16)*(1-A9) -> 308.75 | E9: =IF(B9=0,0,C9/B9) -> 1.0125
A10: 0.4 | B10: =AVERAGE('Loss Scenarios'!F5:F16)*A10 -> 55.986667 | C10: =B10*(1+Assumptions!B20)*(1-Assumptions!B15) -> 56.6865 | D10: =MAX('Loss Scenarios'!F5:F16)*(1-A10) -> 285 | E10: =IF(B10=0,0,C10/B10) -> 1.0125
A11: 0.5 | B11: =AVERAGE('Loss Scenarios'!F5:F16)*A11 -> 69.983333 | C11: =B11*(1+Assumptions!B20)*(1-Assumptions!B15) -> 70.858125 | D11: =MAX('Loss Scenarios'!F5:F16)*(1-A11) -> 237.5 | E11: =IF(B11=0,0,C11/B11) -> 1.0125
A14: B. XoL LAYER 1 — VARYING ATTACHMENT POINT
A15: Attachment (¥B) | B15: Limit (¥B) | C15: Avg Ceded Loss (¥B) | D15: ROL | E15: Premium (¥B)
A16: 5 | B16: 20 | C16: =SUMPRODUCT(MIN(MAX('Loss Scenarios'!F5:F16-A16,0),B16))/12 -> 1.6666667 | D16: =IF(B16=0,0,C16/B16) -> 0.083333333 | E16: =C16*(1+Assumptions!B20) -> 2.25
A17: 10 | B17: 20 | C17: =SUMPRODUCT(MIN(MAX('Loss Scenarios'!F5:F16-A17,0),B17))/12 -> 1.6666667 | D17: =IF(B17=0,0,C17/B17) -> 0.083333333 | E17: =C17*(1+Assumptions!B20) -> 2.25
A18: 15 | B18: 20 | C18: =SUMPRODUCT(MIN(MAX('Loss Scenarios'!F5:F16-A18,0),B18))/12 -> 1.6666667 | D18: =IF(B18=0,0,C18/B18) -> 0.083333333 | E18: =C18*(1+Assumptions!B20) -> 2.25
A19: 20 | B19: 20 | C19: =SUMPRODUCT(MIN(MAX('Loss Scenarios'!F5:F16-A19,0),B19))/12 -> 1.6666667 | D19: =IF(B19=0,0,C19/B19) -> 0.083333333 | E19: =C19*(1+Assumptions!B20) -> 2.25
A20: 30 | B20: 20 | C20: =SUMPRODUCT(MIN(MAX('Loss Scenarios'!F5:F16-A20,0),B20))/12 -> 1.6666667 | D20: =IF(B20=0,0,C20/B20) -> 0.083333333 | E20: =C20*(1+Assumptions!B20) -> 2.25
A21: 50 | B21: 20 | C21: =SUMPRODUCT(MIN(MAX('Loss Scenarios'!F5:F16-A21,0),B21))/12 -> 1.6666667 | D21: =IF(B21=0,0,C21/B21) -> 0.083333333 | E21: =C21*(1+Assumptions!B20) -> 2.25

Sheet Broker Advisory
A1: BROKER ADVISORY MEMORANDUM
A2: Prepared for: [Hypothetical Japanese Cedent] | Prepared by: Edison Li | Date: March 2026
A5: TO: Chief Reinsurance Officer, [Cedent Name]
A6: FROM: Gallagher Re Tokyo — Reinsurance Advisory
A7: RE: FY2026 Property Catastrophe Reinsurance Program — Structure Recommendation
A9: EXECUTIVE SUMMARY
A11: This memorandum presents our analysis of two reinsurance structures for your Japanese property catastrophe portfolio (estimated TSI: ¥2,000B). Based on scenario analysis across 12 historical and hypothetical catastrophe events, we recommend a layered Excess of Loss (XoL) program as the primary risk transfer mechanism, supplemented by a modest Quota Share on the working layer for frequency protection.
A13: KEY FINDINGS
A15: 1. Tail Risk Protection: The XoL program reduces your maximum single-event retention significantly compared to a standalone 30% Quota Share. For extreme scenarios (Nankai Trough M8.5+, Tokyo Inland M7.3), the XoL structure caps reinsurer-funded recovery at each layer limit, providing defined protection at the point of greatest balance sheet impact.
A17: 2. Cost Efficiency: On a cost-per-unit-of-ceded-loss basis, XoL is more capital-efficient for peak perils. Quota Share spreads cost proportionally across all events, including small losses where the cedent has adequate retention capacity. This results in higher total premium for equivalent tail protection.
A19: 3. Frequency vs. Severity Trade-off: Quota Share provides automatic protection for attritional and frequency losses (e.g., minor earthquake swarms, moderate typhoon seasons). If the cedent's priority is earnings stability rather than pure balance sheet protection, a blended approach incorporating Quota Share on the working layer may be appropriate.
A21: RECOMMENDATION
... A34: We welcome the opportunity to discuss this analysis in detail at your convenience.

Sheet Dashboard
A1: VISUAL DASHBOARD — Reinsurance Structure Analysis
A3: Chart Data (linked from Pricing & Comparison)
A4: Metric | B4: XoL Program | C4: Quota Share 30%
A5: Total Premium (¥B) | B5: ='Pricing & Comparison'!B25 -> 73.8 | C5: ='Pricing & Comparison'!C25 -> 56.6865
A6: Avg Ceded Loss (¥B) | B6: ='Pricing & Comparison'!B26 -> 54.666667 | C6: ='Pricing & Comparison'!C26 -> 41.99
A7: Max Cedent Retention (¥B) | B7: ='Pricing & Comparison'!B27 -> 770 | C7: ='Pricing & Comparison'!C27 -> 0
A8: Cost per ¥1B Ceded | B8: ='Pricing & Comparison'!B28 -> 1.35 | C8: ='Pricing & Comparison'!C28 -> 1.35
A30: Max Retention Data
A31: XoL Program | B31: ='Pricing & Comparison'!B27 -> 770
A32: Quota Share 30% | B32: ='Pricing & Comparison'!C27 -> 0
